[
  {
    "riding": "Ajax",
    "pc": 27,
    "ndp": 14,
    "lib": 56,
    "bloc": 0,
    "gpc": 2,
    "other": 2
  },
  {
    "riding": "Algoma—Manitoulin—Kapuskasing",
    "pc": 26,
    "ndp": 45,
    "lib": 19,
    "bloc": 0,
    "gpc": 3,
    "other": 7
  },
  {
    "riding": "Aurora—Oak Ridges—Richmond Hill",
    "pc": 36,
    "ndp": 11,
    "lib": 47,
    "bloc": 0,
    "gpc": 0,
    "other": 6
  },
  {
    "riding": "Barrie—Innisfil",
    "pc": 41,
    "ndp": 27,
    "lib": 27,
    "bloc": 0,
    "gpc": 0,
    "other": 6
  },
  {
    "riding": "Barrie—Springwater—Oro-Medonte",
    "pc": 40,
    "ndp": 26,
    "lib": 29,
    "bloc": 0,
    "gpc": 0,
    "other": 5
  },
  {
    "riding": "Bay of Quinte",
    "pc": 36,
    "ndp": 19,
    "lib": 35,
    "bloc": 0,
    "gpc": 4,
    "other": 6
  },
  {
    "riding": "Beaches—East York",
    "pc": 0,
    "ndp": 28,
    "lib": 61,
    "bloc": 0,
    "gpc": 5,
    "other": 6
  },
  {
    "riding": "Brampton Centre",
    "pc": 25,
    "ndp": 24,
    "lib": 46,
    "bloc": 0,
    "gpc": 0,
    "other": 6
  },
  {
    "riding": "Brampton East",
    "pc": 21,
    "ndp": 32,
    "lib": 43,
    "bloc": 0,
    "gpc": 0,
    "other": 5
  },
  {
    "riding": "Brampton North",
    "pc": 29,
    "ndp": 22,
    "lib": 48,
    "bloc": 0,
    "gpc": 0,
    "other": 2
  },
  {
    "riding": "Brampton South",
    "pc": 27,
    "ndp": 22,
    "lib": 45,
    "bloc": 0,
    "gpc": 0,
    "other": 6
  },
  {
    "riding": "Brampton West",
    "pc": 24,
    "ndp": 23,
    "lib": 48,
    "bloc": 0,
    "gpc": 0,
    "other": 6
  },
  {
    "riding": "Brantford—Brant",
    "pc": 40,
    "ndp": 21,
    "lib": 28,
    "bloc": 0,
    "gpc": 4,
    "other": 8
  },
  {
    "riding": "Bruce—Grey—Owen Sound",
    "pc": 45,
    "ndp": 15,
    "lib": 26,
    "bloc": 0,
    "gpc": 6,
    "other": 8
  },
  {
    "riding": "Burlington",
    "pc": 34,
    "ndp": 12,
    "lib": 45,
    "bloc": 0,
    "gpc": 4,
    "other": 4
  },
  {
    "riding": "Cambridge",
    "pc": 29,
    "ndp": 22,
    "lib": 35,
    "bloc": 0,
    "gpc": 5,
    "other": 9
  },
  {
    "riding": "Carleton",
    "pc": 48,
    "ndp": 12,
    "lib": 32,
    "bloc": 0,
    "gpc": 3,
    "other": 5
  },
  {
    "riding": "Chatham-Kent—Leamington",
    "pc": 46,
    "ndp": 16,
    "lib": 28,
    "bloc": 0,
    "gpc": 2,
    "other": 7
  },
  {
    "riding": "Davenport",
    "pc": 8,
    "ndp": 46,
    "lib": 38,
    "bloc": 0,
    "gpc": 3,
    "other": 5
  },
  {
    "riding": "Don Valley East",
    "pc": 24,
    "ndp": 16,
    "lib": 55,
    "bloc": 0,
    "gpc": 0,
    "other": 4
  },
  {
    "riding": "Don Valley North",
    "pc": 35,
    "ndp": 11,
    "lib": 47,
    "bloc": 0,
    "gpc": 2,
    "other": 4
  },
  {
    "riding": "Don Valley West",
    "pc": 32,
    "ndp": 10,
    "lib": 50,
    "bloc": 0,
    "gpc": 3,
    "other": 5
  },
  {
    "riding": "Dufferin—Caledon",
    "pc": 42,
    "ndp": 13,
    "lib": 30,
    "bloc": 0,
    "gpc": 8,
    "other": 7
  },
  {
    "riding": "Durham",
    "pc": 39,
    "ndp": 26,
    "lib": 29,
    "bloc": 0,
    "gpc": 0,
    "other": 6
  },
  {
    "riding": "Eglinton—Lawrence",
    "pc": 34,
    "ndp": 11,
    "lib": 49,
    "bloc": 0,
    "gpc": 2,
    "other": 4
  },
  {
    "riding": "Elgin—Middlesex—London",
    "pc": 37,
    "ndp": 21,
    "lib": 32,
    "bloc": 0,
    "gpc": 3,
    "other": 8
  },
  {
    "riding": "Essex",
    "pc": 42,
    "ndp": 37,
    "lib": 14,
    "bloc": 0,
    "gpc": 2,
    "other": 6
  },
  {
    "riding": "Etobicoke Centre",
    "pc": 33,
    "ndp": 12,
    "lib": 51,
    "bloc": 0,
    "gpc": 0,
    "other": 5
  },
  {
    "riding": "Etobicoke North",
    "pc": 20,
    "ndp": 16,
    "lib": 57,
    "bloc": 0,
    "gpc": 0,
    "other": 7
  },
  {
    "riding": "Etobicoke—Lakeshore",
    "pc": 30,
    "ndp": 14,
    "lib": 48,
    "bloc": 0,
    "gpc": 4,
    "other": 5
  },
  {
    "riding": "Flamborough—Glanbrook",
    "pc": 40,
    "ndp": 19,
    "lib": 32,
    "bloc": 0,
    "gpc": 4,
    "other": 5
  },
  {
    "riding": "Glengarry—Prescott—Russell",
    "pc": 36,
    "ndp": 13,
    "lib": 42,
    "bloc": 0,
    "gpc": 2,
    "other": 7
  },
  {
    "riding": "Guelph",
    "pc": 19,
    "ndp": 14,
    "lib": 39,
    "bloc": 0,
    "gpc": 21,
    "other": 7
  },
  {
    "riding": "Haldimand—Norfolk",
    "pc": 43,
    "ndp": 25,
    "lib": 22,
    "bloc": 0,
    "gpc": 0,
    "other": 10
  },
  {
    "riding": "Haliburton—Kawartha Lakes—Brock",
    "pc": 51,
    "ndp": 17,
    "lib": 22,
    "bloc": 0,
    "gpc": 6,
    "other": 5
  },
  {
    "riding": "Hamilton Centre",
    "pc": 13,
    "ndp": 51,
    "lib": 23,
    "bloc": 0,
    "gpc": 5,
    "other": 8
  },
  {
    "riding": "Hamilton East—Stoney Creek",
    "pc": 25,
    "ndp": 31,
    "lib": 33,
    "bloc": 0,
    "gpc": 4,
    "other": 6
  },
  {
    "riding": "Hamilton Mountain",
    "pc": 24,
    "ndp": 38,
    "lib": 28,
    "bloc": 0,
    "gpc": 4,
    "other": 6
  },
  {
    "riding": "Hamilton West—Ancaster—Dundas",
    "pc": 25,
    "ndp": 22,
    "lib": 43,
    "bloc": 0,
    "gpc": 5,
    "other": 5
  },
  {
    "riding": "Hastings—Lennox and Addington",
    "pc": 43,
    "ndp": 15,
    "lib": 32,
    "bloc": 0,
    "gpc": 4,
    "other": 6
  },
  {
    "riding": "Humber River—Black Creek",
    "pc": 16,
    "ndp": 22,
    "lib": 56,
    "bloc": 0,
    "gpc": 1,
    "other": 5
  },
  {
    "riding": "Huron—Bruce",
    "pc": 49,
    "ndp": 18,
    "lib": 28,
    "bloc": 0,
    "gpc": 0,
    "other": 5
  },
  {
    "riding": "Kanata—Carleton",
    "pc": 33,
    "ndp": 19,
    "lib": 39,
    "bloc": 0,
    "gpc": 4,
    "other": 4
  },
  {
    "riding": "Kenora",
    "pc": 32,
    "ndp": 34,
    "lib": 25,
    "bloc": 0,
    "gpc": 3,
    "other": 6
  },
  {
    "riding": "Kingston and the Islands",
    "pc": 20,
    "ndp": 26,
    "lib": 42,
    "bloc": 0,
    "gpc": 6,
    "other": 6
  },
  {
    "riding": "King—Vaughan",
    "pc": 43,
    "ndp": 9,
    "lib": 42,
    "bloc": 0,
    "gpc": 2,
    "other": 5
  },
  {
    "riding": "Kitchener Centre",
    "pc": 28,
    "ndp": 24,
    "lib": 26,
    "bloc": 0,
    "gpc": 19,
    "other": 4
  },
  {
    "riding": "Kitchener South—Hespeler",
    "pc": 32,
    "ndp": 15,
    "lib": 39,
    "bloc": 0,
    "gpc": 8,
    "other": 6
  },
  {
    "riding": "Kitchener—Conestoga",
    "pc": 37,
    "ndp": 13,
    "lib": 37,
    "bloc": 0,
    "gpc": 7,
    "other": 5
  },
  {
    "riding": "Lambton—Kent—Middlesex",
    "pc": 50,
    "ndp": 18,
    "lib": 21,
    "bloc": 0,
    "gpc": 4,
    "other": 8
  },
  {
    "riding": "Lanark—Frontenac—Kingston",
    "pc": 49,
    "ndp": 17,
    "lib": 20,
    "bloc": 0,
    "gpc": 8,
    "other": 6
  },
  {
    "riding": "Leeds-Grenville-Thousand Islands and Rideau Lakes",
    "pc": 50,
    "ndp": 16,
    "lib": 21,
    "bloc": 0,
    "gpc": 6,
    "other": 5
  },
  {
    "riding": "London North Centre",
    "pc": 22,
    "ndp": 24,
    "lib": 41,
    "bloc": 0,
    "gpc": 5,
    "other": 7
  },
  {
    "riding": "London West",
    "pc": 25,
    "ndp": 29,
    "lib": 39,
    "bloc": 0,
    "gpc": 0,
    "other": 6
  },
  {
    "riding": "London—Fanshawe",
    "pc": 24,
    "ndp": 47,
    "lib": 23,
    "bloc": 0,
    "gpc": 0,
    "other": 6
  },
  {
    "riding": "Markham—Stouffville",
    "pc": 30,
    "ndp": 13,
    "lib": 54,
    "bloc": 0,
    "gpc": 1,
    "other": 1
  },
  {
    "riding": "Markham—Thornhill",
    "pc": 35,
    "ndp": 10,
    "lib": 48,
    "bloc": 0,
    "gpc": 1,
    "other": 5
  },
  {
    "riding": "Markham—Unionville",
    "pc": 48,
    "ndp": 11,
    "lib": 36,
    "bloc": 0,
    "gpc": 0,
    "other": 5
  },
  {
    "riding": "Milton",
    "pc": 34,
    "ndp": 9,
    "lib": 49,
    "bloc": 0,
    "gpc": 3,
    "other": 5
  },
  {
    "riding": "Mississauga Centre",
    "pc": 30,
    "ndp": 12,
    "lib": 51,
    "bloc": 0,
    "gpc": 1,
    "other": 5
  },
  {
    "riding": "Mississauga East—Cooksville",
    "pc": 33,
    "ndp": 13,
    "lib": 49,
    "bloc": 0,
    "gpc": 0,
    "other": 5
  },
  {
    "riding": "Mississauga—Erin Mills",
    "pc": 34,
    "ndp": 12,
    "lib": 48,
    "bloc": 0,
    "gpc": 2,
    "other": 5
  },
  {
    "riding": "Mississauga—Lakeshore",
    "pc": 36,
    "ndp": 10,
    "lib": 47,
    "bloc": 0,
    "gpc": 3,
    "other": 4
  },
  {
    "riding": "Mississauga—Malton",
    "pc": 24,
    "ndp": 16,
    "lib": 54,
    "bloc": 0,
    "gpc": 1,
    "other": 5
  },
  {
    "riding": "Mississauga—Streetsville",
    "pc": 34,
    "ndp": 12,
    "lib": 46,
    "bloc": 0,
    "gpc": 2,
    "other": 5
  },
  {
    "riding": "Nepean",
    "pc": 33,
    "ndp": 16,
    "lib": 42,
    "bloc": 0,
    "gpc": 4,
    "other": 5
  },
  {
    "riding": "Newmarket—Aurora",
    "pc": 38,
    "ndp": 13,
    "lib": 38,
    "bloc": 0,
    "gpc": 4,
    "other": 7
  },
  {
    "riding": "Niagara Centre",
    "pc": 32,
    "ndp": 23,
    "lib": 36,
    "bloc": 0,
    "gpc": 4,
    "other": 6
  },
  {
    "riding": "Niagara Falls",
    "pc": 33,
    "ndp": 22,
    "lib": 28,
    "bloc": 0,
    "gpc": 3,
    "other": 15
  },
  {
    "riding": "Niagara West",
    "pc": 47,
    "ndp": 14,
    "lib": 27,
    "bloc": 0,
    "gpc": 4,
    "other": 8
  },
  {
    "riding": "Nickel Belt",
    "pc": 20,
    "ndp": 29,
    "lib": 40,
    "bloc": 0,
    "gpc": 3,
    "other": 7
  },
  {
    "riding": "Nipissing—Timiskaming",
    "pc": 26,
    "ndp": 27,
    "lib": 36,
    "bloc": 0,
    "gpc": 0,
    "other": 11
  },
  {
    "riding": "Northumberland—Peterborough South",
    "pc": 40,
    "ndp": 15,
    "lib": 34,
    "bloc": 0,
    "gpc": 6,
    "other": 6
  },
  {
    "riding": "Oakville",
    "pc": 37,
    "ndp": 10,
    "lib": 44,
    "bloc": 0,
    "gpc": 4,
    "other": 5
  },
  {
    "riding": "Oakville North—Burlington",
    "pc": 39,
    "ndp": 10,
    "lib": 44,
    "bloc": 0,
    "gpc": 2,
    "other": 4
  },
  {
    "riding": "Orléans",
    "pc": 28,
    "ndp": 14,
    "lib": 51,
    "bloc": 0,
    "gpc": 3,
    "other": 5
  },
  {
    "riding": "Oshawa",
    "pc": 40,
    "ndp": 31,
    "lib": 20,
    "bloc": 0,
    "gpc": 3,
    "other": 6
  },
  {
    "riding": "Ottawa Centre",
    "pc": 19,
    "ndp": 30,
    "lib": 39,
    "bloc": 0,
    "gpc": 5,
    "other": 6
  },
  {
    "riding": "Ottawa South",
    "pc": 23,
    "ndp": 20,
    "lib": 49,
    "bloc": 0,
    "gpc": 3,
    "other": 5
  },
  {
    "riding": "Ottawa West—Nepean",
    "pc": 28,
    "ndp": 21,
    "lib": 41,
    "bloc": 0,
    "gpc": 4,
    "other": 6
  },
  {
    "riding": "Ottawa—Vanier",
    "pc": 17,
    "ndp": 24,
    "lib": 47,
    "bloc": 0,
    "gpc": 5,
    "other": 8
  },
  {
    "riding": "Oxford",
    "pc": 48,
    "ndp": 22,
    "lib": 15,
    "bloc": 0,
    "gpc": 5,
    "other": 10
  },
  {
    "riding": "Parkdale—High Park",
    "pc": 12,
    "ndp": 33,
    "lib": 46,
    "bloc": 0,
    "gpc": 4,
    "other": 5
  },
  {
    "riding": "Parry Sound—Muskoka",
    "pc": 42,
    "ndp": 15,
    "lib": 27,
    "bloc": 0,
    "gpc": 11,
    "other": 4
  },
  {
    "riding": "Perth—Wellington",
    "pc": 47,
    "ndp": 23,
    "lib": 24,
    "bloc": 0,
    "gpc": 0,
    "other": 7
  },
  {
    "riding": "Peterborough—Kawartha",
    "pc": 40,
    "ndp": 23,
    "lib": 26,
    "bloc": 0,
    "gpc": 5,
    "other": 6
  },
  {
    "riding": "Pickering—Uxbridge",
    "pc": 29,
    "ndp": 19,
    "lib": 46,
    "bloc": 0,
    "gpc": 0,
    "other": 6
  },
  {
    "riding": "Renfrew—Nipissing—Pembroke",
    "pc": 49,
    "ndp": 15,
    "lib": 16,
    "bloc": 0,
    "gpc": 3,
    "other": 16
  },
  {
    "riding": "Richmond Hill",
    "pc": 40,
    "ndp": 14,
    "lib": 41,
    "bloc": 0,
    "gpc": 0,
    "other": 5
  },
  {
    "riding": "Sarnia—Lambton",
    "pc": 50,
    "ndp": 23,
    "lib": 17,
    "bloc": 0,
    "gpc": 2,
    "other": 8
  },
  {
    "riding": "Sault Ste. Marie",
    "pc": 31,
    "ndp": 29,
    "lib": 35,
    "bloc": 0,
    "gpc": 0,
    "other": 6
  },
  {
    "riding": "Scarborough Centre",
    "pc": 22,
    "ndp": 16,
    "lib": 48,
    "bloc": 0,
    "gpc": 0,
    "other": 15
  },
  {
    "riding": "Scarborough North",
    "pc": 29,
    "ndp": 15,
    "lib": 52,
    "bloc": 0,
    "gpc": 0,
    "other": 4
  },
  {
    "riding": "Scarborough Southwest",
    "pc": 19,
    "ndp": 19,
    "lib": 53,
    "bloc": 0,
    "gpc": 3,
    "other": 5
  },
  {
    "riding": "Scarborough—Agincourt",
    "pc": 38,
    "ndp": 11,
    "lib": 46,
    "bloc": 0,
    "gpc": 1,
    "other": 4
  },
  {
    "riding": "Scarborough—Guildwood",
    "pc": 21,
    "ndp": 15,
    "lib": 56,
    "bloc": 0,
    "gpc": 0,
    "other": 7
  },
  {
    "riding": "Scarborough—Rouge Park",
    "pc": 20,
    "ndp": 18,
    "lib": 57,
    "bloc": 0,
    "gpc": 0,
    "other": 5
  },
  {
    "riding": "Simcoe North",
    "pc": 43,
    "ndp": 15,
    "lib": 28,
    "bloc": 0,
    "gpc": 7,
    "other": 7
  },
  {
    "riding": "Simcoe—Grey",
    "pc": 43,
    "ndp": 15,
    "lib": 28,
    "bloc": 0,
    "gpc": 8,
    "other": 6
  },
  {
    "riding": "Spadina—Fort York",
    "pc": 22,
    "ndp": 12,
    "lib": 50,
    "bloc": 0,
    "gpc": 3,
    "other": 14
  },
  {
    "riding": "St. Catharines",
    "pc": 31,
    "ndp": 24,
    "lib": 36,
    "bloc": 0,
    "gpc": 4,
    "other": 5
  },
  {
    "riding": "Stormont—Dundas—South Glengarry",
    "pc": 55,
    "ndp": 16,
    "lib": 20,
    "bloc": 0,
    "gpc": 2,
    "other": 6
  },
  {
    "riding": "Sudbury",
    "pc": 19,
    "ndp": 34,
    "lib": 40,
    "bloc": 0,
    "gpc": 0,
    "other": 7
  },
  {
    "riding": "Thornhill",
    "pc": 53,
    "ndp": 9,
    "lib": 32,
    "bloc": 0,
    "gpc": 2,
    "other": 4
  },
  {
    "riding": "Thunder Bay—Rainy River",
    "pc": 30,
    "ndp": 29,
    "lib": 34,
    "bloc": 0,
    "gpc": 2,
    "other": 5
  },
  {
    "riding": "Thunder Bay—Superior North",
    "pc": 25,
    "ndp": 24,
    "lib": 39,
    "bloc": 0,
    "gpc": 5,
    "other": 6
  },
  {
    "riding": "Timmins—James Bay",
    "pc": 26,
    "ndp": 46,
    "lib": 21,
    "bloc": 0,
    "gpc": 0,
    "other": 8
  },
  {
    "riding": "Toronto Centre",
    "pc": 12,
    "ndp": 1,
    "lib": 72,
    "bloc": 0,
    "gpc": 11,
    "other": 4
  },
  {
    "riding": "Toronto—Danforth",
    "pc": 9,
    "ndp": 38,
    "lib": 43,
    "bloc": 0,
    "gpc": 4,
    "other": 6
  },
  {
    "riding": "Toronto—St. Paul's",
    "pc": 22,
    "ndp": 18,
    "lib": 50,
    "bloc": 0,
    "gpc": 4,
    "other": 5
  },
  {
    "riding": "University—Rosedale",
    "pc": 16,
    "ndp": 25,
    "lib": 48,
    "bloc": 0,
    "gpc": 5,
    "other": 6
  },
  {
    "riding": "Vaughan—Woodbridge",
    "pc": 37,
    "ndp": 10,
    "lib": 46,
    "bloc": 0,
    "gpc": 1,
    "other": 6
  },
  {
    "riding": "Waterloo",
    "pc": 24,
    "ndp": 17,
    "lib": 48,
    "bloc": 0,
    "gpc": 7,
    "other": 5
  },
  {
    "riding": "Wellington—Halton Hills",
    "pc": 47,
    "ndp": 13,
    "lib": 25,
    "bloc": 0,
    "gpc": 9,
    "other": 6
  },
  {
    "riding": "Whitby",
    "pc": 37,
    "ndp": 16,
    "lib": 40,
    "bloc": 0,
    "gpc": 3,
    "other": 4
  },
  {
    "riding": "Willowdale",
    "pc": 36,
    "ndp": 11,
    "lib": 45,
    "bloc": 0,
    "gpc": 2,
    "other": 6
  },
  {
    "riding": "Windsor West",
    "pc": 19,
    "ndp": 45,
    "lib": 30,
    "bloc": 0,
    "gpc": 0,
    "other": 6
  },
  {
    "riding": "Windsor—Tecumseh",
    "pc": 26,
    "ndp": 33,
    "lib": 31,
    "bloc": 0,
    "gpc": 2,
    "other": 7
  },
  {
    "riding": "York Centre",
    "pc": 34,
    "ndp": 16,
    "lib": 48,
    "bloc": 0,
    "gpc": 0,
    "other": 3
  },
  {
    "riding": "York South—Weston",
    "pc": 20,
    "ndp": 20,
    "lib": 54,
    "bloc": 0,
    "gpc": 2,
    "other": 5
  },
  {
    "riding": "York—Simcoe",
    "pc": 45,
    "ndp": 23,
    "lib": 23,
    "bloc": 0,
    "gpc": 0,
    "other": 10
  },
  {
    "riding": "Abitibi—Baie-James—Nunavik—Eeyou",
    "pc": 20,
    "ndp": 12,
    "lib": 27,
    "bloc": 33,
    "gpc": 3,
    "other": 5
  },
  {
    "riding": "Abitibi—Témiscamingue",
    "pc": 18,
    "ndp": 10,
    "lib": 24,
    "bloc": 42,
    "gpc": 3,
    "other": 3
  },
  {
    "riding": "Ahuntsic-Cartierville",
    "pc": 10,
    "ndp": 11,
    "lib": 52,
    "bloc": 18,
    "gpc": 6,
    "other": 3
  },
  {
    "riding": "Alfred-Pellan",
    "pc": 13,
    "ndp": 7,
    "lib": 47,
    "bloc": 25,
    "gpc": 3,
    "other": 4
  },
  {
    "riding": "Argenteuil—La Petite-Nation",
    "pc": 15,
    "ndp": 11,
    "lib": 39,
    "bloc": 32,
    "gpc": 0,
    "other": 4
  },
  {
    "riding": "Avignon—La Mitis—Matane—Matapédia",
    "pc": 10,
    "ndp": 5,
    "lib": 33,
    "bloc": 48,
    "gpc": 0,
    "other": 3
  },
  {
    "riding": "Beauce",
    "pc": 41,
    "ndp": 2,
    "lib": 9,
    "bloc": 9,
    "gpc": 2,
    "other": 36
  },
  {
    "riding": "Beauport-Côte-de-Beaupré-Île d'Orléans-Charlevoix",
    "pc": 33,
    "ndp": 5,
    "lib": 19,
    "bloc": 32,
    "gpc": 2,
    "other": 9
  },
  {
    "riding": "Beauport—Limoilou",
    "pc": 30,
    "ndp": 11,
    "lib": 24,
    "bloc": 27,
    "gpc": 4,
    "other": 5
  },
  {
    "riding": "Bécancour—Nicolet—Saurel",
    "pc": 19,
    "ndp": 5,
    "lib": 17,
    "bloc": 53,
    "gpc": 3,
    "other": 3
  },
  {
    "riding": "Bellechasse—Les Etchemins—Lévis",
    "pc": 55,
    "ndp": 5,
    "lib": 15,
    "bloc": 19,
    "gpc": 3,
    "other": 5
  },
  {
    "riding": "Beloeil—Chambly",
    "pc": 8,
    "ndp": 14,
    "lib": 22,
    "bloc": 48,
    "gpc": 4,
    "other": 3
  },
  {
    "riding": "Berthier—Maskinongé",
    "pc": 14,
    "ndp": 19,
    "lib": 15,
    "bloc": 47,
    "gpc": 2,
    "other": 4
  },
  {
    "riding": "Bourassa",
    "pc": 9,
    "ndp": 8,
    "lib": 57,
    "bloc": 19,
    "gpc": 3,
    "other": 4
  },
  {
    "riding": "Brome—Missisquoi",
    "pc": 15,
    "ndp": 8,
    "lib": 38,
    "bloc": 30,
    "gpc": 5,
    "other": 4
  },
  {
    "riding": "Brossard—Saint-Lambert",
    "pc": 13,
    "ndp": 13,
    "lib": 55,
    "bloc": 17,
    "gpc": 0,
    "other": 3
  },
  {
    "riding": "Charlesbourg—Haute-Saint-Charles",
    "pc": 43,
    "ndp": 7,
    "lib": 19,
    "bloc": 23,
    "gpc": 3,
    "other": 5
  },
  {
    "riding": "Châteauguay—Lacolle",
    "pc": 14,
    "ndp": 7,
    "lib": 38,
    "bloc": 33,
    "gpc": 3,
    "other": 4
  },
  {
    "riding": "Chicoutimi—Le Fjord",
    "pc": 42,
    "ndp": 6,
    "lib": 16,
    "bloc": 30,
    "gpc": 3,
    "other": 4
  },
  {
    "riding": "Compton—Stanstead",
    "pc": 17,
    "ndp": 9,
    "lib": 37,
    "bloc": 28,
    "gpc": 5,
    "other": 4
  },
  {
    "riding": "Dorval—Lachine—LaSalle",
    "pc": 13,
    "ndp": 11,
    "lib": 52,
    "bloc": 14,
    "gpc": 5,
    "other": 5
  },
  {
    "riding": "Drummond",
    "pc": 20,
    "ndp": 18,
    "lib": 17,
    "bloc": 41,
    "gpc": 0,
    "other": 4
  },
  {
    "riding": "Gaspésie—Les Îles-de-la-Madeleine",
    "pc": 10,
    "ndp": 6,
    "lib": 43,
    "bloc": 37,
    "gpc": 0,
    "other": 4
  },
  {
    "riding": "Gatineau",
    "pc": 13,
    "ndp": 11,
    "lib": 52,
    "bloc": 18,
    "gpc": 4,
    "other": 3
  },
  {
    "riding": "Hochelaga",
    "pc": 6,
    "ndp": 21,
    "lib": 34,
    "bloc": 30,
    "gpc": 5,
    "other": 4
  },
  {
    "riding": "Honoré-Mercier",
    "pc": 12,
    "ndp": 8,
    "lib": 58,
    "bloc": 17,
    "gpc": 2,
    "other": 3
  },
  {
    "riding": "Hull—Aylmer",
    "pc": 12,
    "ndp": 13,
    "lib": 53,
    "bloc": 11,
    "gpc": 7,
    "other": 4
  },
  {
    "riding": "Joliette",
    "pc": 11,
    "ndp": 4,
    "lib": 22,
    "bloc": 55,
    "gpc": 4,
    "other": 4
  },
  {
    "riding": "Jonquière",
    "pc": 24,
    "ndp": 13,
    "lib": 26,
    "bloc": 32,
    "gpc": 2,
    "other": 3
  },
  {
    "riding": "La Pointe-de-l'Île",
    "pc": 9,
    "ndp": 13,
    "lib": 30,
    "bloc": 44,
    "gpc": 0,
    "other": 3
  },
  {
    "riding": "La Prairie",
    "pc": 11,
    "ndp": 7,
    "lib": 30,
    "bloc": 45,
    "gpc": 4,
    "other": 2
  },
  {
    "riding": "Lac-Saint-Jean",
    "pc": 27,
    "ndp": 5,
    "lib": 24,
    "bloc": 40,
    "gpc": 2,
    "other": 3
  },
  {
    "riding": "Lac-Saint-Louis",
    "pc": 18,
    "ndp": 12,
    "lib": 57,
    "bloc": 2,
    "gpc": 7,
    "other": 4
  },
  {
    "riding": "LaSalle—Émard—Verdun",
    "pc": 9,
    "ndp": 16,
    "lib": 43,
    "bloc": 21,
    "gpc": 7,
    "other": 5
  },
  {
    "riding": "Laurentides—Labelle",
    "pc": 10,
    "ndp": 6,
    "lib": 32,
    "bloc": 44,
    "gpc": 5,
    "other": 4
  },
  {
    "riding": "Laurier—Sainte-Marie",
    "pc": 5,
    "ndp": 25,
    "lib": 42,
    "bloc": 20,
    "gpc": 6,
    "other": 4
  },
  {
    "riding": "Laval—Les Îles",
    "pc": 19,
    "ndp": 8,
    "lib": 47,
    "bloc": 17,
    "gpc": 4,
    "other": 4
  },
  {
    "riding": "Lévis—Lotbinière",
    "pc": 49,
    "ndp": 6,
    "lib": 15,
    "bloc": 21,
    "gpc": 3,
    "other": 7
  },
  {
    "riding": "Longueuil—Charles-LeMoyne",
    "pc": 10,
    "ndp": 10,
    "lib": 39,
    "bloc": 33,
    "gpc": 6,
    "other": 3
  },
  {
    "riding": "Longueuil—Saint-Hubert",
    "pc": 9,
    "ndp": 8,
    "lib": 41,
    "bloc": 36,
    "gpc": 3,
    "other": 3
  },
  {
    "riding": "Louis-Hébert",
    "pc": 21,
    "ndp": 7,
    "lib": 40,
    "bloc": 24,
    "gpc": 4,
    "other": 5
  },
  {
    "riding": "Louis-Saint-Laurent",
    "pc": 49,
    "ndp": 6,
    "lib": 19,
    "bloc": 18,
    "gpc": 3,
    "other": 5
  },
  {
    "riding": "Manicouagan",
    "pc": 23,
    "ndp": 6,
    "lib": 19,
    "bloc": 50,
    "gpc": 0,
    "other": 2
  },
  {
    "riding": "Marc-Aurèle-Fortin",
    "pc": 12,
    "ndp": 11,
    "lib": 45,
    "bloc": 29,
    "gpc": 0,
    "other": 3
  },
  {
    "riding": "Mégantic—L'Érable",
    "pc": 54,
    "ndp": 4,
    "lib": 14,
    "bloc": 21,
    "gpc": 2,
    "other": 5
  },
  {
    "riding": "Mirabel",
    "pc": 12,
    "ndp": 8,
    "lib": 24,
    "bloc": 48,
    "gpc": 5,
    "other": 4
  },
  {
    "riding": "Montarville",
    "pc": 9,
    "ndp": 12,
    "lib": 35,
    "bloc": 40,
    "gpc": 0,
    "other": 3
  },
  {
    "riding": "Montcalm",
    "pc": 12,
    "ndp": 6,
    "lib": 19,
    "bloc": 55,
    "gpc": 4,
    "other": 4
  },
  {
    "riding": "Montmagny—L'Islet—Kamouraska—Rivière-du-Loup",
    "pc": 47,
    "ndp": 8,
    "lib": 15,
    "bloc": 27,
    "gpc": 0,
    "other": 2
  },
  {
    "riding": "Mount Royal",
    "pc": 28,
    "ndp": 8,
    "lib": 55,
    "bloc": 2,
    "gpc": 5,
    "other": 3
  },
  {
    "riding": "Notre-Dame-de-Grâce—Westmount",
    "pc": 14,
    "ndp": 15,
    "lib": 55,
    "bloc": 2,
    "gpc": 10,
    "other": 4
  },
  {
    "riding": "Outremont",
    "pc": 9,
    "ndp": 19,
    "lib": 46,
    "bloc": 11,
    "gpc": 12,
    "other": 3
  },
  {
    "riding": "Papineau",
    "pc": 6,
    "ndp": 19,
    "lib": 51,
    "bloc": 13,
    "gpc": 7,
    "other": 5
  },
  {
    "riding": "Pierre-Boucher—Les Patriotes—Verchères",
    "pc": 11,
    "ndp": 10,
    "lib": 29,
    "bloc": 48,
    "gpc": 0,
    "other": 2
  },
  {
    "riding": "Pierrefonds—Dollard",
    "pc": 20,
    "ndp": 13,
    "lib": 56,
    "bloc": 6,
    "gpc": 0,
    "other": 5
  },
  {
    "riding": "Pontiac",
    "pc": 28,
    "ndp": 11,
    "lib": 37,
    "bloc": 14,
    "gpc": 6,
    "other": 4
  },
  {
    "riding": "Portneuf—Jacques-Cartier",
    "pc": 48,
    "ndp": 8,
    "lib": 19,
    "bloc": 20,
    "gpc": 0,
    "other": 6
  },
  {
    "riding": "Québec",
    "pc": 18,
    "ndp": 11,
    "lib": 33,
    "bloc": 29,
    "gpc": 5,
    "other": 5
  },
  {
    "riding": "Repentigny",
    "pc": 10,
    "ndp": 9,
    "lib": 27,
    "bloc": 50,
    "gpc": 0,
    "other": 4
  },
  {
    "riding": "Richmond—Arthabaska",
    "pc": 50,
    "ndp": 8,
    "lib": 15,
    "bloc": 24,
    "gpc": 0,
    "other": 3
  },
  {
    "riding": "Rimouski-Neigette—Témiscouata—Les Basques",
    "pc": 11,
    "ndp": 26,
    "lib": 22,
    "bloc": 38,
    "gpc": 0,
    "other": 3
  },
  {
    "riding": "Rivière-des-Mille-Îles",
    "pc": 10,
    "ndp": 8,
    "lib": 35,
    "bloc": 38,
    "gpc": 5,
    "other": 4
  },
  {
    "riding": "Rivière-du-Nord",
    "pc": 15,
    "ndp": 11,
    "lib": 22,
    "bloc": 49,
    "gpc": 0,
    "other": 3
  },
  {
    "riding": "Rosemont—La Petite-Patrie",
    "pc": 4,
    "ndp": 43,
    "lib": 23,
    "bloc": 21,
    "gpc": 6,
    "other": 3
  },
  {
    "riding": "Saint-Hyacinthe—Bagot",
    "pc": 17,
    "ndp": 21,
    "lib": 21,
    "bloc": 38,
    "gpc": 0,
    "other": 3
  },
  {
    "riding": "Saint-Jean",
    "pc": 13,
    "ndp": 7,
    "lib": 29,
    "bloc": 42,
    "gpc": 5,
    "other": 3
  },
  {
    "riding": "Saint-Laurent",
    "pc": 20,
    "ndp": 13,
    "lib": 58,
    "bloc": 5,
    "gpc": 0,
    "other": 3
  },
  {
    "riding": "Saint-Léonard—Saint-Michel",
    "pc": 14,
    "ndp": 8,
    "lib": 58,
    "bloc": 7,
    "gpc": 0,
    "other": 14
  },
  {
    "riding": "Saint-Maurice—Champlain",
    "pc": 19,
    "ndp": 5,
    "lib": 39,
    "bloc": 30,
    "gpc": 3,
    "other": 4
  },
  {
    "riding": "Salaberry—Suroît",
    "pc": 12,
    "ndp": 10,
    "lib": 29,
    "bloc": 44,
    "gpc": 0,
    "other": 4
  },
  {
    "riding": "Shefford",
    "pc": 16,
    "ndp": 6,
    "lib": 32,
    "bloc": 38,
    "gpc": 5,
    "other": 4
  },
  {
    "riding": "Sherbrooke",
    "pc": 13,
    "ndp": 28,
    "lib": 29,
    "bloc": 23,
    "gpc": 4,
    "other": 3
  },
  {
    "riding": "Terrebonne",
    "pc": 10,
    "ndp": 7,
    "lib": 28,
    "bloc": 48,
    "gpc": 4,
    "other": 3
  },
  {
    "riding": "Thérèse-De Blainville",
    "pc": 11,
    "ndp": 7,
    "lib": 35,
    "bloc": 39,
    "gpc": 4,
    "other": 3
  },
  {
    "riding": "Trois-Rivières",
    "pc": 29,
    "ndp": 16,
    "lib": 25,
    "bloc": 25,
    "gpc": 2,
    "other": 3
  },
  {
    "riding": "Vaudreuil—Soulanges",
    "pc": 14,
    "ndp": 10,
    "lib": 47,
    "bloc": 21,
    "gpc": 5,
    "other": 3
  },
  {
    "riding": "Ville-Marie—Le Sud-Ouest—Île-des-Soeurs",
    "pc": 11,
    "ndp": 15,
    "lib": 53,
    "bloc": 10,
    "gpc": 7,
    "other": 4
  },
  {
    "riding": "Vimy",
    "pc": 13,
    "ndp": 11,
    "lib": 48,
    "bloc": 24,
    "gpc": 0,
    "other": 3
  },
  {
    "riding": "Abbotsford",
    "pc": 46,
    "ndp": 22,
    "lib": 23,
    "bloc": 0,
    "gpc": 3,
    "other": 6
  },
  {
    "riding": "Burnaby North—Seymour",
    "pc": 17,
    "ndp": 37,
    "lib": 33,
    "bloc": 0,
    "gpc": 5,
    "other": 8
  },
  {
    "riding": "Burnaby South",
    "pc": 25,
    "ndp": 48,
    "lib": 21,
    "bloc": 0,
    "gpc": 1,
    "other": 5
  },
  {
    "riding": "Cariboo—Prince George",
    "pc": 49,
    "ndp": 20,
    "lib": 20,
    "bloc": 0,
    "gpc": 5,
    "other": 7
  },
  {
    "riding": "Central Okanagan—Similkameen—Nicola",
    "pc": 49,
    "ndp": 20,
    "lib": 22,
    "bloc": 0,
    "gpc": 3,
    "other": 6
  },
  {
    "riding": "Chilliwack—Hope",
    "pc": 44,
    "ndp": 21,
    "lib": 22,
    "bloc": 0,
    "gpc": 5,
    "other": 8
  },
  {
    "riding": "Cloverdale—Langley City",
    "pc": 40,
    "ndp": 18,
    "lib": 28,
    "bloc": 0,
    "gpc": 0,
    "other": 14
  },
  {
    "riding": "Coquitlam—Port Coquitlam",
    "pc": 28,
    "ndp": 35,
    "lib": 33,
    "bloc": 0,
    "gpc": 0,
    "other": 4
  },
  {
    "riding": "Courtenay—Alberni",
    "pc": 29,
    "ndp": 48,
    "lib": 12,
    "bloc": 0,
    "gpc": 9,
    "other": 3
  },
  {
    "riding": "Cowichan—Malahat—Langford",
    "pc": 26,
    "ndp": 43,
    "lib": 14,
    "bloc": 0,
    "gpc": 12,
    "other": 5
  },
  {
    "riding": "Delta",
    "pc": 36,
    "ndp": 22,
    "lib": 33,
    "bloc": 0,
    "gpc": 2,
    "other": 7
  },
  {
    "riding": "Esquimalt—Saanich—Sooke",
    "pc": 17,
    "ndp": 41,
    "lib": 16,
    "bloc": 0,
    "gpc": 18,
    "other": 7
  },
  {
    "riding": "Fleetwood—Port Kells",
    "pc": 29,
    "ndp": 29,
    "lib": 35,
    "bloc": 0,
    "gpc": 1,
    "other": 5
  },
  {
    "riding": "Kamloops—Thompson—Cariboo",
    "pc": 41,
    "ndp": 18,
    "lib": 27,
    "bloc": 0,
    "gpc": 8,
    "other": 6
  },
  {
    "riding": "Kelowna—Lake Country",
    "pc": 47,
    "ndp": 16,
    "lib": 29,
    "bloc": 0,
    "gpc": 2,
    "other": 6
  },
  {
    "riding": "Kootenay—Columbia",
    "pc": 39,
    "ndp": 41,
    "lib": 10,
    "bloc": 0,
    "gpc": 4,
    "other": 6
  },
  {
    "riding": "Langley—Aldergrove",
    "pc": 45,
    "ndp": 21,
    "lib": 24,
    "bloc": 0,
    "gpc": 3,
    "other": 8
  },
  {
    "riding": "Mission—Matsqui—Fraser Canyon",
    "pc": 39,
    "ndp": 25,
    "lib": 25,
    "bloc": 0,
    "gpc": 5,
    "other": 6
  },
  {
    "riding": "Nanaimo—Ladysmith",
    "pc": 23,
    "ndp": 29,
    "lib": 13,
    "bloc": 0,
    "gpc": 29,
    "other": 6
  },
  {
    "riding": "New Westminster—Burnaby",
    "pc": 20,
    "ndp": 50,
    "lib": 20,
    "bloc": 0,
    "gpc": 3,
    "other": 6
  },
  {
    "riding": "North Island—Powell River",
    "pc": 27,
    "ndp": 46,
    "lib": 14,
    "bloc": 0,
    "gpc": 8,
    "other": 6
  },
  {
    "riding": "North Okanagan—Shuswap",
    "pc": 47,
    "ndp": 19,
    "lib": 21,
    "bloc": 0,
    "gpc": 6,
    "other": 8
  },
  {
    "riding": "North Vancouver",
    "pc": 24,
    "ndp": 24,
    "lib": 42,
    "bloc": 0,
    "gpc": 6,
    "other": 4
  },
  {
    "riding": "Pitt Meadows—Maple Ridge",
    "pc": 31,
    "ndp": 33,
    "lib": 30,
    "bloc": 0,
    "gpc": 0,
    "other": 6
  },
  {
    "riding": "Port Moody—Coquitlam",
    "pc": 33,
    "ndp": 34,
    "lib": 29,
    "bloc": 0,
    "gpc": 0,
    "other": 5
  },
  {
    "riding": "Prince George—Peace River—Northern Rockies",
    "pc": 65,
    "ndp": 13,
    "lib": 13,
    "bloc": 0,
    "gpc": 2,
    "other": 7
  },
  {
    "riding": "Richmond Centre",
    "pc": 47,
    "ndp": 18,
    "lib": 26,
    "bloc": 0,
    "gpc": 2,
    "other": 6
  },
  {
    "riding": "Saanich—Gulf Islands",
    "pc": 19,
    "ndp": 21,
    "lib": 17,
    "bloc": 0,
    "gpc": 37,
    "other": 5
  },
  {
    "riding": "Skeena—Bulkley Valley",
    "pc": 28,
    "ndp": 45,
    "lib": 11,
    "bloc": 0,
    "gpc": 4,
    "other": 12
  },
  {
    "riding": "South Okanagan—West Kootenay",
    "pc": 34,
    "ndp": 42,
    "lib": 15,
    "bloc": 0,
    "gpc": 3,
    "other": 7
  },
  {
    "riding": "South Surrey—White Rock",
    "pc": 35,
    "ndp": 21,
    "lib": 40,
    "bloc": 0,
    "gpc": 0,
    "other": 4
  },
  {
    "riding": "Steveston—Richmond East",
    "pc": 40,
    "ndp": 19,
    "lib": 33,
    "bloc": 0,
    "gpc": 3,
    "other": 5
  },
  {
    "riding": "Surrey Centre",
    "pc": 24,
    "ndp": 40,
    "lib": 26,
    "bloc": 0,
    "gpc": 2,
    "other": 8
  },
  {
    "riding": "Surrey—Newton",
    "pc": 17,
    "ndp": 34,
    "lib": 44,
    "bloc": 0,
    "gpc": 0,
    "other": 4
  },
  {
    "riding": "Vancouver Centre",
    "pc": 19,
    "ndp": 29,
    "lib": 40,
    "bloc": 0,
    "gpc": 7,
    "other": 6
  },
  {
    "riding": "Vancouver East",
    "pc": 8,
    "ndp": 59,
    "lib": 18,
    "bloc": 0,
    "gpc": 8,
    "other": 6
  },
  {
    "riding": "Vancouver Granville",
    "pc": 31,
    "ndp": 24,
    "lib": 35,
    "bloc": 0,
    "gpc": 1,
    "other": 9
  },
  {
    "riding": "Vancouver Kingsway",
    "pc": 15,
    "ndp": 60,
    "lib": 19,
    "bloc": 0,
    "gpc": 2,
    "other": 4
  },
  {
    "riding": "Vancouver Quadra",
    "pc": 24,
    "ndp": 19,
    "lib": 45,
    "bloc": 0,
    "gpc": 8,
    "other": 4
  },
  {
    "riding": "Vancouver South",
    "pc": 32,
    "ndp": 26,
    "lib": 38,
    "bloc": 0,
    "gpc": 0,
    "other": 4
  },
  {
    "riding": "Victoria",
    "pc": 9,
    "ndp": 41,
    "lib": 24,
    "bloc": 0,
    "gpc": 20,
    "other": 5
  },
  {
    "riding": "West Vancouver—Sunshine Coast—Sea to Sky Country",
    "pc": 44,
    "ndp": 16,
    "lib": 25,
    "bloc": 0,
    "gpc": 8,
    "other": 7
  },
  {
    "riding": "Banff—Airdrie",
    "pc": 51,
    "ndp": 20,
    "lib": 13,
    "bloc": 0,
    "gpc": 4,
    "other": 12
  },
  {
    "riding": "Battle River—Crowfoot",
    "pc": 67,
    "ndp": 15,
    "lib": 6,
    "bloc": 0,
    "gpc": 3,
    "other": 10
  },
  {
    "riding": "Bow River",
    "pc": 65,
    "ndp": 14,
    "lib": 9,
    "bloc": 0,
    "gpc": 0,
    "other": 12
  },
  {
    "riding": "Calgary Centre",
    "pc": 39,
    "ndp": 18,
    "lib": 30,
    "bloc": 0,
    "gpc": 4,
    "other": 9
  },
  {
    "riding": "Calgary Confederation",
    "pc": 38,
    "ndp": 20,
    "lib": 25,
    "bloc": 0,
    "gpc": 8,
    "other": 9
  },
  {
    "riding": "Calgary Forest Lawn",
    "pc": 39,
    "ndp": 19,
    "lib": 24,
    "bloc": 0,
    "gpc": 3,
    "other": 14
  },
  {
    "riding": "Calgary Heritage",
    "pc": 52,
    "ndp": 18,
    "lib": 17,
    "bloc": 0,
    "gpc": 3,
    "other": 10
  },
  {
    "riding": "Calgary Midnapore",
    "pc": 56,
    "ndp": 18,
    "lib": 13,
    "bloc": 0,
    "gpc": 3,
    "other": 9
  },
  {
    "riding": "Calgary Nose Hill",
    "pc": 52,
    "ndp": 18,
    "lib": 18,
    "bloc": 0,
    "gpc": 3,
    "other": 9
  },
  {
    "riding": "Calgary Rocky Ridge",
    "pc": 51,
    "ndp": 17,
    "lib": 21,
    "bloc": 0,
    "gpc": 3,
    "other": 9
  },
  {
    "riding": "Calgary Shepard",
    "pc": 57,
    "ndp": 18,
    "lib": 14,
    "bloc": 0,
    "gpc": 3,
    "other": 9
  },
  {
    "riding": "Calgary Signal Hill",
    "pc": 51,
    "ndp": 17,
    "lib": 18,
    "bloc": 0,
    "gpc": 3,
    "other": 10
  },
  {
    "riding": "Calgary Skyview",
    "pc": 36,
    "ndp": 14,
    "lib": 39,
    "bloc": 0,
    "gpc": 2,
    "other": 10
  },
  {
    "riding": "Edmonton Centre",
    "pc": 24,
    "ndp": 32,
    "lib": 35,
    "bloc": 0,
    "gpc": 0,
    "other": 8
  },
  {
    "riding": "Edmonton Griesbach",
    "pc": 34,
    "ndp": 41,
    "lib": 17,
    "bloc": 0,
    "gpc": 2,
    "other": 5
  },
  {
    "riding": "Edmonton Manning",
    "pc": 35,
    "ndp": 31,
    "lib": 24,
    "bloc": 0,
    "gpc": 0,
    "other": 10
  },
  {
    "riding": "Edmonton Mill Woods",
    "pc": 33,
    "ndp": 22,
    "lib": 37,
    "bloc": 0,
    "gpc": 0,
    "other": 8
  },
  {
    "riding": "Edmonton Riverbend",
    "pc": 40,
    "ndp": 26,
    "lib": 24,
    "bloc": 0,
    "gpc": 3,
    "other": 7
  },
  {
    "riding": "Edmonton Strathcona",
    "pc": 19,
    "ndp": 61,
    "lib": 12,
    "bloc": 0,
    "gpc": 2,
    "other": 7
  },
  {
    "riding": "Edmonton West",
    "pc": 42,
    "ndp": 27,
    "lib": 22,
    "bloc": 0,
    "gpc": 0,
    "other": 9
  },
  {
    "riding": "Edmonton—Wetaskiwin",
    "pc": 53,
    "ndp": 23,
    "lib": 15,
    "bloc": 0,
    "gpc": 0,
    "other": 9
  },
  {
    "riding": "Foothills",
    "pc": 63,
    "ndp": 15,
    "lib": 8,
    "bloc": 0,
    "gpc": 4,
    "other": 10
  },
  {
    "riding": "Fort McMurray—Cold Lake",
    "pc": 62,
    "ndp": 13,
    "lib": 12,
    "bloc": 0,
    "gpc": 2,
    "other": 12
  },
  {
    "riding": "Grande Prairie—Mackenzie",
    "pc": 66,
    "ndp": 17,
    "lib": 7,
    "bloc": 0,
    "gpc": 0,
    "other": 10
  },
  {
    "riding": "Lakeland",
    "pc": 67,
    "ndp": 14,
    "lib": 6,
    "bloc": 0,
    "gpc": 2,
    "other": 11
  },
  {
    "riding": "Lethbridge",
    "pc": 45,
    "ndp": 29,
    "lib": 17,
    "bloc": 0,
    "gpc": 0,
    "other": 10
  },
  {
    "riding": "Medicine Hat—Cardston—Warner",
    "pc": 60,
    "ndp": 18,
    "lib": 9,
    "bloc": 0,
    "gpc": 2,
    "other": 11
  },
  {
    "riding": "Peace River—Westlock",
    "pc": 62,
    "ndp": 16,
    "lib": 8,
    "bloc": 0,
    "gpc": 3,
    "other": 11
  },
  {
    "riding": "Red Deer—Lacombe",
    "pc": 61,
    "ndp": 20,
    "lib": 8,
    "bloc": 0,
    "gpc": 0,
    "other": 12
  },
  {
    "riding": "Red Deer—Mountain View",
    "pc": 63,
    "ndp": 18,
    "lib": 8,
    "bloc": 0,
    "gpc": 0,
    "other": 11
  },
  {
    "riding": "Sherwood Park—Fort Saskatchewan",
    "pc": 54,
    "ndp": 22,
    "lib": 12,
    "bloc": 0,
    "gpc": 2,
    "other": 9
  },
  {
    "riding": "St. Albert—Edmonton",
    "pc": 43,
    "ndp": 26,
    "lib": 23,
    "bloc": 0,
    "gpc": 0,
    "other": 9
  },
  {
    "riding": "Sturgeon River—Parkland",
    "pc": 58,
    "ndp": 22,
    "lib": 10,
    "bloc": 0,
    "gpc": 0,
    "other": 11
  },
  {
    "riding": "Yellowhead",
    "pc": 63,
    "ndp": 17,
    "lib": 8,
    "bloc": 0,
    "gpc": 0,
    "other": 12
  },
  {
    "riding": "Brandon—Souris",
    "pc": 57,
    "ndp": 20,
    "lib": 12,
    "bloc": 0,
    "gpc": 0,
    "other": 11
  },
  {
    "riding": "Charleswood—St. James—Assiniboia—Headingley",
    "pc": 54,
    "ndp": 9,
    "lib": 34,
    "bloc": 0,
    "gpc": 3,
    "other": 0
  },
  {
    "riding": "Churchill—Keewatinook Aski",
    "pc": 17,
    "ndp": 51,
    "lib": 21,
    "bloc": 0,
    "gpc": 6,
    "other": 6
  },
  {
    "riding": "Dauphin—Swan River—Neepawa",
    "pc": 61,
    "ndp": 12,
    "lib": 11,
    "bloc": 0,
    "gpc": 5,
    "other": 11
  },
  {
    "riding": "Elmwood—Transcona",
    "pc": 37,
    "ndp": 43,
    "lib": 9,
    "bloc": 0,
    "gpc": 3,
    "other": 7
  },
  {
    "riding": "Kildonan—St. Paul",
    "pc": 36,
    "ndp": 20,
    "lib": 35,
    "bloc": 0,
    "gpc": 0,
    "other": 9
  },
  {
    "riding": "Portage—Lisgar",
    "pc": 66,
    "ndp": 10,
    "lib": 11,
    "bloc": 0,
    "gpc": 0,
    "other": 13
  },
  {
    "riding": "Provencher",
    "pc": 61,
    "ndp": 12,
    "lib": 11,
    "bloc": 0,
    "gpc": 7,
    "other": 9
  },
  {
    "riding": "Saint Boniface—Saint Vital",
    "pc": 30,
    "ndp": 15,
    "lib": 41,
    "bloc": 0,
    "gpc": 5,
    "other": 9
  },
  {
    "riding": "Selkirk—Interlake—Eastman",
    "pc": 63,
    "ndp": 16,
    "lib": 9,
    "bloc": 0,
    "gpc": 6,
    "other": 7
  },
  {
    "riding": "Winnipeg Centre",
    "pc": 13,
    "ndp": 44,
    "lib": 30,
    "bloc": 0,
    "gpc": 5,
    "other": 8
  },
  {
    "riding": "Winnipeg North",
    "pc": 18,
    "ndp": 22,
    "lib": 49,
    "bloc": 0,
    "gpc": 3,
    "other": 9
  },
  {
    "riding": "Winnipeg South",
    "pc": 27,
    "ndp": 18,
    "lib": 44,
    "bloc": 0,
    "gpc": 5,
    "other": 6
  },
  {
    "riding": "Winnipeg South Centre",
    "pc": 27,
    "ndp": 16,
    "lib": 44,
    "bloc": 0,
    "gpc": 6,
    "other": 7
  },
  {
    "riding": "Battlefords—Lloydminster",
    "pc": 62,
    "ndp": 17,
    "lib": 9,
    "bloc": 0,
    "gpc": 3,
    "other": 9
  },
  {
    "riding": "Carlton Trail—Eagle Creek",
    "pc": 63,
    "ndp": 17,
    "lib": 6,
    "bloc": 0,
    "gpc": 3,
    "other": 11
  },
  {
    "riding": "Cypress Hills—Grasslands",
    "pc": 65,
    "ndp": 14,
    "lib": 6,
    "bloc": 0,
    "gpc": 2,
    "other": 13
  },
  {
    "riding": "Desnethé—Missinippi—Churchill River",
    "pc": 27,
    "ndp": 35,
    "lib": 30,
    "bloc": 0,
    "gpc": 2,
    "other": 6
  },
  {
    "riding": "Moose Jaw—Lake Centre—Lanigan",
    "pc": 56,
    "ndp": 22,
    "lib": 8,
    "bloc": 0,
    "gpc": 4,
    "other": 10
  },
  {
    "riding": "Prince Albert",
    "pc": 49,
    "ndp": 24,
    "lib": 13,
    "bloc": 0,
    "gpc": 3,
    "other": 11
  },
  {
    "riding": "Regina—Lewvan",
    "pc": 39,
    "ndp": 32,
    "lib": 16,
    "bloc": 0,
    "gpc": 5,
    "other": 9
  },
  {
    "riding": "Regina—Qu'Appelle",
    "pc": 49,
    "ndp": 26,
    "lib": 13,
    "bloc": 0,
    "gpc": 4,
    "other": 9
  },
  {
    "riding": "Regina—Wascana",
    "pc": 55,
    "ndp": 19,
    "lib": 15,
    "bloc": 0,
    "gpc": 3,
    "other": 7
  },
  {
    "riding": "Saskatoon West",
    "pc": 32,
    "ndp": 34,
    "lib": 22,
    "bloc": 0,
    "gpc": 3,
    "other": 8
  },
  {
    "riding": "Saskatoon—Grasswood",
    "pc": 35,
    "ndp": 33,
    "lib": 20,
    "bloc": 0,
    "gpc": 4,
    "other": 8
  },
  {
    "riding": "Saskatoon—University",
    "pc": 39,
    "ndp": 32,
    "lib": 16,
    "bloc": 0,
    "gpc": 4,
    "other": 10
  },
  {
    "riding": "Souris—Moose Mountain",
    "pc": 70,
    "ndp": 13,
    "lib": 7,
    "bloc": 0,
    "gpc": 0,
    "other": 9
  },
  {
    "riding": "Yorkton—Melville",
    "pc": 59,
    "ndp": 18,
    "lib": 9,
    "bloc": 0,
    "gpc": 3,
    "other": 11
  },
  {
    "riding": "Cape Breton—Canso",
    "pc": 39,
    "ndp": 14,
    "lib": 39,
    "bloc": 0,
    "gpc": 0,
    "other": 8
  },
  {
    "riding": "Central Nova",
    "pc": 25,
    "ndp": 18,
    "lib": 47,
    "bloc": 0,
    "gpc": 2,
    "other": 9
  },
  {
    "riding": "Cumberland—Colchester",
    "pc": 49,
    "ndp": 1,
    "lib": 35,
    "bloc": 0,
    "gpc": 9,
    "other": 6
  },
  {
    "riding": "Dartmouth—Cole Harbour",
    "pc": 1,
    "ndp": 32,
    "lib": 64,
    "bloc": 0,
    "gpc": 3,
    "other": 1
  },
  {
    "riding": "Halifax",
    "pc": 15,
    "ndp": 27,
    "lib": 46,
    "bloc": 0,
    "gpc": 6,
    "other": 6
  },
  {
    "riding": "Halifax West",
    "pc": 18,
    "ndp": 26,
    "lib": 51,
    "bloc": 0,
    "gpc": 3,
    "other": 2
  },
  {
    "riding": "Kings—Hants",
    "pc": 21,
    "ndp": 23,
    "lib": 43,
    "bloc": 0,
    "gpc": 6,
    "other": 7
  },
  {
    "riding": "Sackville—Preston—Chezzetcook",
    "pc": 31,
    "ndp": 24,
    "lib": 36,
    "bloc": 0,
    "gpc": 4,
    "other": 5
  },
  {
    "riding": "South Shore—St. Margarets",
    "pc": 30,
    "ndp": 17,
    "lib": 48,
    "bloc": 0,
    "gpc": 4,
    "other": 1
  },
  {
    "riding": "Sydney—Victoria",
    "pc": 32,
    "ndp": 17,
    "lib": 49,
    "bloc": 0,
    "gpc": 0,
    "other": 1
  },
  {
    "riding": "West Nova",
    "pc": 40,
    "ndp": 12,
    "lib": 45,
    "bloc": 0,
    "gpc": 0,
    "other": 4
  },
  {
    "riding": "Acadie—Bathurst",
    "pc": 22,
    "ndp": 15,
    "lib": 60,
    "bloc": 0,
    "gpc": 2,
    "other": 1
  },
  {
    "riding": "Beauséjour",
    "pc": 21,
    "ndp": 7,
    "lib": 48,
    "bloc": 0,
    "gpc": 16,
    "other": 7
  },
  {
    "riding": "Fredericton",
    "pc": 25,
    "ndp": 11,
    "lib": 41,
    "bloc": 0,
    "gpc": 15,
    "other": 7
  },
  {
    "riding": "Fundy Royal",
    "pc": 41,
    "ndp": 15,
    "lib": 25,
    "bloc": 0,
    "gpc": 8,
    "other": 11
  },
  {
    "riding": "Madawaska—Restigouche",
    "pc": 30,
    "ndp": 11,
    "lib": 50,
    "bloc": 0,
    "gpc": 7,
    "other": 3
  },
  {
    "riding": "Miramichi—Grand Lake",
    "pc": 35,
    "ndp": 10,
    "lib": 40,
    "bloc": 0,
    "gpc": 4,
    "other": 11
  },
  {
    "riding": "Moncton—Riverview—Dieppe",
    "pc": 27,
    "ndp": 11,
    "lib": 43,
    "bloc": 0,
    "gpc": 9,
    "other": 10
  },
  {
    "riding": "New Brunswick Southwest",
    "pc": 49,
    "ndp": 13,
    "lib": 26,
    "bloc": 0,
    "gpc": 4,
    "other": 8
  },
  {
    "riding": "Saint John—Rothesay",
    "pc": 28,
    "ndp": 10,
    "lib": 43,
    "bloc": 0,
    "gpc": 3,
    "other": 17
  },
  {
    "riding": "Tobique—Mactaquac",
    "pc": 62,
    "ndp": 11,
    "lib": 17,
    "bloc": 0,
    "gpc": 5,
    "other": 6
  },
  {
    "riding": "Avalon",
    "pc": 29,
    "ndp": 20,
    "lib": 49,
    "bloc": 0,
    "gpc": 0,
    "other": 1
  },
  {
    "riding": "Bonavista—Burin—Trinity",
    "pc": 36,
    "ndp": 13,
    "lib": 49,
    "bloc": 0,
    "gpc": 0,
    "other": 2
  },
  {
    "riding": "Coast of Bays—Central—Notre Dame",
    "pc": 31,
    "ndp": 20,
    "lib": 48,
    "bloc": 0,
    "gpc": 0,
    "other": 2
  },
  {
    "riding": "Labrador",
    "pc": 25,
    "ndp": 32,
    "lib": 41,
    "bloc": 0,
    "gpc": 0,
    "other": 1
  },
  {
    "riding": "Long Range Mountains",
    "pc": 26,
    "ndp": 22,
    "lib": 48,
    "bloc": 0,
    "gpc": 0,
    "other": 4
  },
  {
    "riding": "St. John's East",
    "pc": 18,
    "ndp": 46,
    "lib": 35,
    "bloc": 0,
    "gpc": 0,
    "other": 1
  },
  {
    "riding": "St. John's South—Mount Pearl",
    "pc": 22,
    "ndp": 23,
    "lib": 51,
    "bloc": 0,
    "gpc": 0,
    "other": 5
  },
  {
    "riding": "Cardigan",
    "pc": 26,
    "ndp": 11,
    "lib": 52,
    "bloc": 0,
    "gpc": 7,
    "other": 5
  },
  {
    "riding": "Charlottetown",
    "pc": 29,
    "ndp": 17,
    "lib": 36,
    "bloc": 0,
    "gpc": 14,
    "other": 4
  },
  {
    "riding": "Egmont",
    "pc": 36,
    "ndp": 8,
    "lib": 46,
    "bloc": 0,
    "gpc": 9,
    "other": 1
  },
  {
    "riding": "Malpeque",
    "pc": 31,
    "ndp": 7,
    "lib": 44,
    "bloc": 0,
    "gpc": 16,
    "other": 2
  },
  {
    "riding": "Yukon",
    "pc": 38,
    "ndp": 18,
    "lib": 30,
    "bloc": 0,
    "gpc": 5,
    "other": 8
  },
  {
    "riding": "Northwest Territories",
    "pc": 31,
    "ndp": 16,
    "lib": 40,
    "bloc": 0,
    "gpc": 5,
    "other": 9
  },
  {
    "riding": "Nunavut",
    "pc": 30,
    "ndp": 38,
    "lib": 29,
    "bloc": 0,
    "gpc": 0,
    "other": 3
  }
]